odd_sel/odd_sel.v
`timescale 1ns/1ns
module odd_sel(
input [31:0] bus,
input sel,
output check
);
//*************code***********//
//sel为1时奇校验，为0时偶校验
//连续异或结果为奇校验，连续同或结果为偶校验  采用按位异或同或
reg odd = 0;
always @(*) begin
    if(sel) begin
        odd = ^bus;
    end
    else begin
        odd = ~^bus;
    end
    
end
assign check = odd;
/* 其他答案
`timescale 1ns/1ns
module odd_sel(
input [31:0] bus,
input sel,
output check
);

wire odd;
assign odd = ^bus;
assign check = sel?odd:~odd;

endmodule 
*/
//*************code***********//
endmodule

odd_sel/tb_odd_sel.v
`timescale 1ns/1ns
`include "./odd_sel.v"

module testbench();
    wire check;
    reg sel = 0;
    reg clk = 0;
    
    reg [31:0] bus = 32'b0;
    odd_sel odd_sel_test(
        .bus(bus),
        .sel(sel),
        .check(check)
    );
    initial
    begin
        #20  sel = ~sel;
        #60  sel = ~sel;
        #60  sel = ~sel;
        #50  sel = ~sel;
        $finish;
        
    end
    always
    begin
    #5 clk = ~clk;
    end
    always
    begin
    #20 bus = bus+1;
    end

    initial begin
        $dumpfile("out.vcd");
        // This will dump all signal, which may not be useful
        //$dumpvars;
        // dumping only this module
        //$dumpvars(1, testbench);
        // dumping only these variable
        // the first number (level) is actually useless
        $dumpvars(0, testbench);
    end
endmodule

odd_sel/out.vcd
$date
	Thu Feb 08 14:21:38 2024
$end
$version
	Icarus Verilog
$end
$timescale
	1ns
$end
$scope module testbench $end
$var wire 1 ! check $end
$var reg 32 " bus [31:0] $end
$var reg 1 # clk $end
$var reg 1 $ sel $end
$scope module odd_sel_test $end
$var wire 32 % bus [31:0] $end
$var wire 1 ! check $end
$var wire 1 $ sel $end
$var reg 1 & odd $end
$upscope $end
$upscope $end
$enddefinitions $end
#0
$dumpvars
1&
b0 %
0$
0#
b0 "
1!
$end
#5
1#
#10
0#
#15
1#
#20
0#
b1 "
b1 %
1$
#25
1#
#30
0#
#35
1#
#40
0#
b10 "
b10 %
#45
1#
#50
0#
#55
1#
#60
0!
0&
0#
b11 "
b11 %
#65
1#
#70
0#
#75
1#
#80
0#
b100 "
b100 %
0$
#85
1#
#90
0#
#95
1#
#100
1!
1&
0#
b101 "
b101 %
#105
1#
#110
0#
#115
1#
#120
0#
b110 "
b110 %
#125
1#
#130
0#
#135
1#
#140
0#
b111 "
b111 %
1$
#145
1#
#150
0#
#155
1#
#160
0#
b1000 "
b1000 %
#165
1#
#170
0#
#175
1#
#180
0!
0&
0#
b1001 "
b1001 %
#185
1#
#190
1!
1&
0#
0$
