counter/counter.v
module counter(
    input clk,
    input rst,
    output reg [31:0] counter
);
always @(posedge clk or negedge rst) begin
    if (!rst) begin
        counter <= 1'b0;
    end else if(counter < 32'd100) begin           //100进制
        counter <= counter + 1'b1;
    end else begin
        counter <= 1'b0;
    end
end

endmodule

counter/tb_counter.v
`include "./counter.v"
module tb_counter;

reg clk;
reg rst;
wire [31:0] counter;
counter counter_inst(
    .clk(clk),
    .rst(rst),
    .counter(counter)
);

initial begin
    $dumpfile("tb_counter.vcd");
    $dumpvars(0,tb_counter);
end

initial begin
    rst = 0;
    clk = 0;
    #10
    rst = 1;
    #10000;
    $finish;
end

always #1 clk  = !clk;

endmodule

counter/tb_counter.vcd
$date
	Wed Feb 07 00:13:58 2024
$end
$version
	Icarus Verilog
$end
$timescale
	1s
$end
$scope module tb_counter $end
$var wire 32 ! counter [31:0] $end
$var reg 1 " clk $end
$var reg 1 # rst $end
$scope module counter_inst $end
$var wire 1 " clk $end
$var wire 1 # rst $end
$var reg 32 $ counter [31:0] $end
$upscope $end
$upscope $end
$enddefinitions $end
$comment Show the parameter values. $end
$dumpall
$end
#0
$dumpvars
b0 $
0#
0"
b0 !
$end
#1
1"
#2
0"
#3
1"
#4
0"
#5
1"
#6
0"
#7
1"
#8
0"
#9
1"
#10
0"
1#
#11
b1 !
b1 $
1"
#12
0"
#13
b10 !
b10 $
1"
#14
0"
#15
b11 !
b11 $
1"
#16
0"
#17
b100 !
b100 $
1"
#18
0"
#19
b101 !
b101 $
1"
#20
0"
#21
b110 !
b110 $
1"
#22
0"
#23
b111 !
b111 $
1"
#24
0"
#25
b1000 !
b1000 $
1"
#26
0"
#27
b1001 !
b1001 $
1"
#28
0"
#29
b1010 !
b1010 $
1"
#30
0"
#31
b1011 !
b1011 $
1"
#32
0"
#33
b1100 !
b1100 $
1"
#34
0"
#35
b1101 !
b1101 $
1"
#36
0"
#37
b1110 !
b1110 $
1"
#38
0"
#39
b1111 !
b1111 $
1"
#40
0"
#41
b10000 !
b10000 $
1"
#42
0"
#43
b10001 !
b10001 $
1"
#44
0"
#45
b10010 !
b10010 $
1"
#46
0"
#47
b10011 !
b10011 $
1"
#48
0"
#49
b10100 !
b10100 $
1"
#50
0"
#51
b10101 !
b10101 $
1"
#52
0"
#53
b10110 !
b10110 $
1"
#54
0"
#55
b10111 !
b10111 $
1"
#56
0"
#57
b11000 !
b11000 $
1"
#58
0"
#59
b11001 !
b11001 $
1"
#60
0"
#61
b11010 !
b11010 $
1"
#62
0"
#63
b11011 !
b11011 $
1"
#64
0"
#65
b11100 !
b11100 $
1"
#66
0"
#67
b11101 !
b11101 $
1"
#68
0"
#69
b11110 !
b11110 $
1"
#70
0"
#71
b11111 !
b11111 $
1"
#72
0"
#73
b100000 !
b100000 $
1"
#74
0"
#75
b100001 !
b100001 $
1"
#76
0"
#77
b100010 !
b100010 $
1"
#78
0"
#79
b100011 !
b100011 $
1"
#80
0"
#81
b100100 !
b100100 $
1"
#82
0"
#83
b100101 !
b100101 $
1"
#84
0"
#85
b100110 !
b100110 $
1"
#86
0"
#87
b100111 !
b100111 $
1"
#88
0"
#89
b101000 !
b101000 $
1"
#90
0"
#91
b101001 !
b101001 $
1"
#92
0"
#93
b101010 !
b101010 $
1"
#94
0"
#95
b101011 !
b101011 $
1"
#96
0"
#97
b101100 !
b101100 $
1"
#98
0"
#99
b101101 !
b101101 $
1"
#100
0"
#101
b101110 !
b101110 $
1"
#102
0"
#103
b101111 !
b101111 $
1"
#104
0"
#105
b110000 !
b110000 $
1"
#106
0"
#107
b110001 !
b110001 $
1"
#108
0"
#109
b110010 !
b110010 $
1"
#110
0"
#111
b110011 !
b110011 $
1"
#112
0"
#113
b110100 !
b110100 $
1"
#114
0"
#115
b110101 !
b110101 $
1"
#116
0"
#117
b110110 !
b110110 $
1"
#118
0"
#119
b110111 !
b110111 $
1"
#120
0"
#121
b111000 !
b111000 $
1"
#122
0"
#123
b111001 !
b111001 $
1"
#124
0"
#125
b111010 !
b111010 $
1"
#126
0"
#127
b111011 !
b111011 $
1"
#128
0"
#129
b111100 !
b111100 $
1"
#130
0"
#131
b111101 !
b111101 $
1"
#132
0"
#133
b111110 !
b111110 $
1"
#134
0"
#135
b111111 !
b111111 $
1"
#136
0"
#137
b1000000 !
b1000000 $
1"
#138
0"
#139
b1000001 !
b1000001 $
1"
#140
0"
#141
b1000010 !
b1000010 $
1"
#142
0"
#143
b1000011 !
b1000011 $
1"
#144
0"
#145
b1000100 !
b1000100 $
1"
#146
0"
#147
b1000101 !
b1000101 $
1"
#148
0"
#149
b1000110 !
b1000110 $
1"
#150
0"
#151
b1000111 !
b1000111 $
1"
#152
0"
#153
b1001000 !
b1001000 $
1"
#154
0"
#155
b1001001 !
b1001001 $
1"
#156
0"
#157
b1001010 !
b1001010 $
1"
#158
0"
#159
b1001011 !
b1001011 $
1"
#160
0"
#161
b1001100 !
b1001100 $
1"
#162
0"
#163
b1001101 !
b1001101 $
1"
#164
0"
#165
b1001110 !
b1001110 $
1"
#166
0"
#167
b1001111 !
b1001111 $
1"
#168
0"
#169
b1010000 !
b1010000 $
1"
#170
0"
#171
b1010001 !
b1010001 $
1"
#172
0"
#173
b1010010 !
b1010010 $
1"
#174
0"
#175
b1010011 !
b1010011 $
1"
#176
0"
#177
b1010100 !
b1010100 $
1"
#178
0"
#179
b1010101 !
b1010101 $
1"
#180
0"
#181
b1010110 !
b1010110 $
1"
#182
0"
#183
b1010111 !
b1010111 $
1"
#184
0"
#185
b1011000 !
b1011000 $
1"
#186
0"
#187
b1011001 !
b1011001 $
1"
#188
0"
#189
b1011010 !
b1011010 $
1"
#190
0"
#191
b1011011 !
b1011011 $
1"
#192
0"
#193
b1011100 !
b1011100 $
1"
#194
0"
#195
b1011101 !
b1011101 $
1"
#196
0"
#197
b1011110 !
b1011110 $
1"
#198
0"
#199
b1011111 !
b1011111 $
1"
#200
0"
#201
b1100000 !
b1100000 $
1"
#202
0"
#203
b1100001 !
b1100001 $
1"
#204
0"
#205
b1100010 !
b1100010 $
1"
#206
0"
#207
b1100011 !
b1100011 $
1"
#208
0"
#209
b1100100 !
b1100100 $
1"
#210
0"
#211
b0 !
b0 $
1"
#212
0"
#213
b1 !
b1 $
1"
#214
0"
#215
b10 !
b10 $
1"
#216
0"
#217
b11 !
b11 $
1"
#218
0"
#219
b100 !
b100 $
1"
#220
0"
#221
b101 !
b101 $
1"
#222
0"
#223
b110 !
b110 $
1"
#224
0"
#225
b111 !
b111 $
1"
#226
0"
#227
b1000 !
b1000 $
1"
#228
0"
#229
b1001 !
b1001 $
1"
#230
0"
#231
b1010 !
b1010 $
1"
#232
0"
#233
b1011 !
b1011 $
1"
#234
0"
#235
b1100 !
b1100 $
1"
#236
0"
#237
b1101 !
b1101 $
1"
#238
0"
#239
b1110 !
b1110 $
1"
#240
0"
#241
b1111 !
b1111 $
1"
#242
0"
#243
b10000 !
b10000 $
1"
#244
0"
#245
b10001 !
b10001 $
1"
#246
0"
#247
b10010 !
b10010 $
1"
#248
0"
#249
b10011 !
b10011 $
1"
#250
0"
#251
b10100 !
b10100 $
1"
#252
0"
#253
b10101 !
b10101 $
1"
#254
0"
#255
b10110 !
b10110 $
1"
#256
0"
#257
b10111 !
b10111 $
1"
#258
0"
#259
b11000 !
b11000 $
1"
#260
0"
#261
b11001 !
b11001 $
1"
#262
0"
#263
b11010 !
b11010 $
1"
#264
0"
#265
b11011 !
b11011 $
1"
#266
0"
#267
b11100 !
b11100 $
1"
#268
0"
#269
b11101 !
b11101 $
1"
#270
0"
#271
b11110 !
b11110 $
1"
#272
0"
#273
b11111 !
b11111 $
1"
#274
0"
#275
b100000 !
b100000 $
1"
#276
0"
#277
b100001 !
b100001 $
1"
#278
0"
#279
b100010 !
b100010 $
1"
#280
0"
#281
b100011 !
b100011 $
1"
#282
0"
#283
b100100 !
b100100 $
1"
#284
0"
#285
b100101 !
b100101 $
1"
#286
0"
#287
b100110 !
b100110 $
1"
#288
0"
#289
b100111 !
b100111 $
1"
#290
0"
#291
b101000 !
b101000 $
1"
#292
0"
#293
b101001 !
b101001 $
1"
#294
0"
#295
b101010 !
b101010 $
1"
#296
0"
#297
b101011 !
b101011 $
1"
#298
0"
#299
b101100 !
b101100 $
1"
#300
0"
#301
b101101 !
b101101 $
1"
#302
0"
#303
b101110 !
b101110 $
1"
#304
0"
#305
b101111 !
b101111 $
1"
#306
0"
#307
b110000 !
b110000 $
1"
#308
0"
#309
b110001 !
b110001 $
1"
#310
0"
#311
b110010 !
b110010 $
1"
#312
0"
#313
b110011 !
b110011 $
1"
#314
0"
#315
b110100 !
b110100 $
1"
#316
0"
#317
b110101 !
b110101 $
1"
#318
0"
#319
b110110 !
b110110 $
1"
#320
0"
#321
b110111 !
b110111 $
1"
#322
0"
#323
b111000 !
b111000 $
1"
#324
0"
#325
b111001 !
b111001 $
1"
#326
0"
#327
b111010 !
b111010 $
1"
#328
0"
#329
b111011 !
b111011 $
1"
#330
0"
#331
b111100 !
b111100 $
1"
#332
0"
#333
b111101 !
b111101 $
1"
#334
0"
#335
b111110 !
b111110 $
1"
#336
0"
#337
b111111 !
b111111 $
1"
#338
0"
#339
b1000000 !
b1000000 $
1"
#340
0"
#341
b1000001 !
b1000001 $
1"
#342
0"
#343
b1000010 !
b1000010 $
1"
#344
0"
#345
b1000011 !
b1000011 $
1"
#346
0"
#347
b1000100 !
b1000100 $
1"
#348
0"
#349
b1000101 !
b1000101 $
1"
#350
0"
#351
b1000110 !
b1000110 $
1"
#352
0"
#353
b1000111 !
b1000111 $
1"
#354
0"
#355
b1001000 !
b1001000 $
1"
#356
0"
#357
b1001001 !
b1001001 $
1"
#358
0"
#359
b1001010 !
b1001010 $
1"
#360
0"
#361
b1001011 !
b1001011 $
1"
#362
0"
#363
b1001100 !
b1001100 $
1"
#364
0"
#365
b1001101 !
b1001101 $
1"
#366
0"
#367
b1001110 !
b1001110 $
1"
#368
0"
#369
b1001111 !
b1001111 $
1"
#370
0"
#371
b1010000 !
b1010000 $
1"
#372
0"
#373
b1010001 !
b1010001 $
1"
#374
0"
#375
b1010010 !
b1010010 $
1"
#376
0"
#377
b1010011 !
b1010011 $
1"
#378
0"
#379
b1010100 !
b1010100 $
1"
#380
0"
#381
b1010101 !
b1010101 $
1"
#382
0"
#383
b1010110 !
b1010110 $
1"
#384
0"
#385
b1010111 !
b1010111 $
1"
#386
0"
#387
b1011000 !
b1011000 $
1"
#388
0"
#389
b1011001 !
b1011001 $
1"
#390
0"
#391
b1011010 !
b1011010 $
1"
#392
0"
#393
b1011011 !
b1011011 $
1"
#394
0"
#395
b1011100 !
b1011100 $
1"
#396
0"
#397
b1011101 !
b1011101 $
1"
#398
0"
#399
b1011110 !
b1011110 $
1"
#400
0"
#401
b1011111 !
b1011111 $
1"
#402
0"
#403
b1100000 !
b1100000 $
1"
#404
0"
#405
b1100001 !
b1100001 $
1"
#406
0"
#407
b1100010 !
b1100010 $
1"
#408
0"
#409
b1100011 !
b1100011 $
1"
#410
0"
#411
b1100100 !
b1100100 $
1"
#412
0"
#413
b0 !
b0 $
1"
#414
0"
#415
b1 !
b1 $
1"
#416
0"
#417
b10 !
b10 $
1"
#418
0"
#419
b11 !
b11 $
1"
#420
0"
#421
b100 !
b100 $
1"
#422
0"
#423
b101 !
b101 $
1"
#424
0"
#425
b110 !
b110 $
1"
#426
0"
#427
b111 !
b111 $
1"
#428
0"
#429
b1000 !
b1000 $
1"
#430
0"
#431
b1001 !
b1001 $
1"
#432
0"
#433
b1010 !
b1010 $
1"
#434
0"
#435
b1011 !
b1011 $
1"
#436
0"
#437
b1100 !
b1100 $
1"
#438
0"
#439
b1101 !
b1101 $
1"
#440
0"
#441
b1110 !
b1110 $
1"
#442
0"
#443
b1111 !
b1111 $
1"
#444
0"
#445
b10000 !
b10000 $
1"
#446
0"
#447
b10001 !
b10001 $
1"
#448
0"
#449
b10010 !
b10010 $
1"
#450
0"
#451
b10011 !
b10011 $
1"
#452
0"
#453
b10100 !
b10100 $
1"
#454
0"
#455
b10101 !
b10101 $
1"
#456
0"
#457
b10110 !
b10110 $
1"
#458
0"
#459
b10111 !
b10111 $
1"
#460
0"
#461
b11000 !
b11000 $
1"
#462
0"
#463
b11001 !
b11001 $
1"
#464
0"
#465
b11010 !
b11010 $
1"
#466
0"
#467
b11011 !
b11011 $
1"
#468
0"
#469
b11100 !
b11100 $
1"
#470
0"
#471
b11101 !
b11101 $
1"
#472
0"
#473
b11110 !
b11110 $
1"
#474
0"
#475
b11111 !
b11111 $
1"
#476
0"
#477
b100000 !
b100000 $
1"
#478
0"
#479
b100001 !
b100001 $
1"
#480
0"
#481
b100010 !
b100010 $
1"
#482
0"
#483
b100011 !
b100011 $
1"
#484
0"
#485
b100100 !
b100100 $
1"
#486
0"
#487
b100101 !
b100101 $
1"
#488
0"
#489
b100110 !
b100110 $
1"
#490
0"
#491
b100111 !
b100111 $
1"
#492
0"
#493
b101000 !
b101000 $
1"
#494
0"
#495
b101001 !
b101001 $
1"
#496
0"
#497
b101010 !
b101010 $
1"
#498
0"
#499
b101011 !
b101011 $
1"
#500
0"
#501
b101100 !
b101100 $
1"
#502
0"
#503
b101101 !
b101101 $
1"
#504
0"
#505
b101110 !
b101110 $
1"
#506
0"
#507
b101111 !
b101111 $
1"
#508
0"
#509
b110000 !
b110000 $
1"
#510
0"
#511
b110001 !
b110001 $
1"
#512
0"
#513
b110010 !
b110010 $
1"
#514
0"
#515
b110011 !
b110011 $
1"
#516
0"
#517
b110100 !
b110100 $
1"
#518
0"
#519
b110101 !
b110101 $
1"
#520
0"
#521
b110110 !
b110110 $
1"
#522
0"
#523
b110111 !
b110111 $
1"
#524
0"
#525
b111000 !
b111000 $
1"
#526
0"
#527
b111001 !
b111001 $
1"
#528
0"
#529
b111010 !
b111010 $
1"
#530
0"
#531
b111011 !
b111011 $
1"
#532
0"
#533
b111100 !
b111100 $
1"
#534
0"
#535
b111101 !
b111101 $
1"
#536
0"
#537
b111110 !
b111110 $
1"
#538
0"
#539
b111111 !
b111111 $
1"
#540
0"
#541
b1000000 !
b1000000 $
1"
#542
0"
#543
b1000001 !
b1000001 $
1"
#544
0"
#545
b1000010 !
b1000010 $
1"
#546
0"
#547
b1000011 !
b1000011 $
1"
#548
0"
#549
b1000100 !
b1000100 $
1"
#550
0"
#551
b1000101 !
b1000101 $
1"
#552
0"
#553
b1000110 !
b1000110 $
1"
#554
0"
#555
b1000111 !
b1000111 $
1"
#556
0"
#557
b1001000 !
b1001000 $
1"
#558
0"
#559
b1001001 !
b1001001 $
1"
#560
0"
#561
b1001010 !
b1001010 $
1"
#562
0"
#563
b1001011 !
b1001011 $
1"
#564
0"
#565
b1001100 !
b1001100 $
1"
#566
0"
#567
b1001101 !
b1001101 $
1"
#568
0"
#569
b1001110 !
b1001110 $
1"
#570
0"
#571
b1001111 !
b1001111 $
1"
#572
0"
#573
b1010000 !
b1010000 $
1"
#574
0"
#575
b1010001 !
b1010001 $
1"
#576
0"
#577
b1010010 !
b1010010 $
1"
#578
0"
#579
b1010011 !
b1010011 $
1"
#580
0"
#581
b1010100 !
b1010100 $
1"
#582
0"
#583
b1010101 !
b1010101 $
1"
#584
0"
#585
b1010110 !
b1010110 $
1"
#586
0"
#587
b1010111 !
b1010111 $
1"
#588
0"
#589
b1011000 !
b1011000 $
1"
#590
0"
#591
b1011001 !
b1011001 $
1"
#592
0"
#593
b1011010 !
b1011010 $
1"
#594
0"
#595
b1011011 !
b1011011 $
1"
#596
0"
#597
b1011100 !
b1011100 $
1"
#598
0"
#599
b1011101 !
b1011101 $
1"
#600
0"
#601
b1011110 !
b1011110 $
1"
#602
0"
#603
b1011111 !
b1011111 $
1"
#604
0"
#605
b1100000 !
b1100000 $
1"
#606
0"
#607
b1100001 !
b1100001 $
1"
#608
0"
#609
b1100010 !
b1100010 $
1"
#610
0"
#611
b1100011 !
b1100011 $
1"
#612
0"
#613
b1100100 !
b1100100 $
1"
#614
0"
#615
b0 !
b0 $
1"
#616
0"
#617
b1 !
b1 $
1"
#618
0"
#619
b10 !
b10 $
1"
#620
0"
#621
b11 !
b11 $
1"
#622
0"
#623
b100 !
b100 $
1"
#624
0"
#625
b101 !
b101 $
1"
#626
0"
#627
b110 !
b110 $
1"
#628
0"
#629
b111 !
b111 $
1"
#630
0"
#631
b1000 !
b1000 $
1"
#632
0"
#633
b1001 !
b1001 $
1"
#634
0"
#635
b1010 !
b1010 $
1"
#636
0"
#637
b1011 !
b1011 $
1"
#638
0"
#639
b1100 !
b1100 $
1"
#640
0"
#641
b1101 !
b1101 $
1"
#642
0"
#643
b1110 !
b1110 $
1"
#644
0"
#645
b1111 !
b1111 $
1"
#646
0"
#647
b10000 !
b10000 $
1"
#648
0"
#649
b10001 !
b10001 $
1"
#650
0"
#651
b10010 !
b10010 $
1"
#652
0"
#653
b10011 !
b10011 $
1"
#654
0"
#655
b10100 !
b10100 $
1"
#656
0"
#657
b10101 !
b10101 $
1"
#658
0"
#659
b10110 !
b10110 $
1"
#660
0"
#661
b10111 !
b10111 $
1"
#662
0"
#663
b11000 !
b11000 $
1"
#664
0"
#665
b11001 !
b11001 $
1"
#666
0"
#667
b11010 !
b11010 $
1"
#668
0"
#669
b11011 !
b11011 $
1"
#670
0"
#671
b11100 !
b11100 $
1"
#672
0"
#673
b11101 !
b11101 $
1"
#674
0"
#675
b11110 !
b11110 $
1"
#676
0"
#677
b11111 !
b11111 $
1"
#678
0"
#679
b100000 !
b100000 $
1"
#680
0"
#681
b100001 !
b100001 $
1"
#682
0"
#683
b100010 !
b100010 $
1"
#684
0"
#685
b100011 !
b100011 $
1"
#686
0"
#687
b100100 !
b100100 $
1"
#688
0"
#689
b100101 !
b100101 $
1"
#690
0"
#691
b100110 !
b100110 $
1"
#692
0"
#693
b100111 !
b100111 $
1"
#694
0"
#695
b101000 !
b101000 $
1"
#696
0"
#697
b101001 !
b101001 $
1"
#698
0"
#699
b101010 !
b101010 $
1"
#700
0"
#701
b101011 !
b101011 $
1"
#702
0"
#703
b101100 !
b101100 $
1"
#704
0"
#705
b101101 !
b101101 $
1"
#706
0"
#707
b101110 !
b101110 $
1"
#708
0"
#709
b101111 !
b101111 $
1"
#710
0"
#711
b110000 !
b110000 $
1"
#712
0"
#713
b110001 !
b110001 $
1"
#714
0"
#715
b110010 !
b110010 $
1"
#716
0"
#717
b110011 !
b110011 $
1"
#718
0"
#719
b110100 !
b110100 $
1"
#720
0"
#721
b110101 !
b110101 $
1"
#722
0"
#723
b110110 !
b110110 $
1"
#724
0"
#725
b110111 !
b110111 $
1"
#726
0"
#727
b111000 !
b111000 $
1"
#728
0"
#729
b111001 !
b111001 $
1"
#730
0"
#731
b111010 !
b111010 $
1"
#732
0"
#733
b111011 !
b111011 $
1"
#734
0"
#735
b111100 !
b111100 $
1"
#736
0"
#737
b111101 !
b111101 $
1"
#738
0"
#739
b111110 !
b111110 $
1"
#740
0"
#741
b111111 !
b111111 $
1"
#742
0"
#743
b1000000 !
b1000000 $
1"
#744
0"
#745
b1000001 !
b1000001 $
1"
#746
0"
#747
b1000010 !
b1000010 $
1"
#748
0"
#749
b1000011 !
b1000011 $
1"
#750
0"
#751
b1000100 !
b1000100 $
1"
#752
0"
#753
b1000101 !
b1000101 $
1"
#754
0"
#755
b1000110 !
b1000110 $
1"
#756
0"
#757
b1000111 !
b1000111 $
1"
#758
0"
#759
b1001000 !
b1001000 $
1"
#760
0"
#761
b1001001 !
b1001001 $
1"
#762
0"
#763
b1001010 !
b1001010 $
1"
#764
0"
#765
b1001011 !
b1001011 $
1"
#766
0"
#767
b1001100 !
b1001100 $
1"
#768
0"
#769
b1001101 !
b1001101 $
1"
#770
0"
#771
b1001110 !
b1001110 $
1"
#772
0"
#773
b1001111 !
b1001111 $
1"
#774
0"
#775
b1010000 !
b1010000 $
1"
#776
0"
#777
b1010001 !
b1010001 $
1"
#778
0"
#779
b1010010 !
b1010010 $
1"
#780
0"
#781
b1010011 !
b1010011 $
1"
#782
0"
#783
b1010100 !
b1010100 $
1"
#784
0"
#785
b1010101 !
b1010101 $
1"
#786
0"
#787
b1010110 !
b1010110 $
1"
#788
0"
#789
b1010111 !
b1010111 $
1"
#790
0"
#791
b1011000 !
b1011000 $
1"
#792
0"
#793
b1011001 !
b1011001 $
1"
#794
0"
#795
b1011010 !
b1011010 $
1"
#796
0"
#797
b1011011 !
b1011011 $
1"
#798
0"
#799
b1011100 !
b1011100 $
1"
#800
0"
#801
b1011101 !
b1011101 $
1"
#802
0"
#803
b1011110 !
b1011110 $
1"
#804
0"
#805
b1011111 !
b1011111 $
1"
#806
0"
#807
b1100000 !
b1100000 $
1"
#808
0"
#809
b1100001 !
b1100001 $
1"
#810
0"
#811
b1100010 !
b1100010 $
1"
#812
0"
#813
b1100011 !
b1100011 $
1"
#814
0"
#815
b1100100 !
b1100100 $
1"
#816
0"
#817
b0 !
b0 $
1"
#818
0"
#819
b1 !
b1 $
1"
#820
0"
#821
b10 !
b10 $
1"
#822
0"
#823
b11 !
b11 $
1"
#824
0"
#825
b100 !
b100 $
1"
#826
0"
#827
b101 !
b101 $
1"
#828
0"
#829
b110 !
b110 $
1"
#830
0"
#831
b111 !
b111 $
1"
#832
0"
#833
b1000 !
b1000 $
1"
#834
0"
#835
b1001 !
b1001 $
1"
#836
0"
#837
b1010 !
b1010 $
1"
#838
0"
#839
b1011 !
b1011 $
1"
#840
0"
#841
b1100 !
b1100 $
1"
#842
0"
#843
b1101 !
b1101 $
1"
#844
0"
#845
b1110 !
b1110 $
1"
#846
0"
#847
b1111 !
b1111 $
1"
#848
0"
#849
b10000 !
b10000 $
1"
#850
0"
#851
b10001 !
b10001 $
1"
#852
0"
#853
b10010 !
b10010 $
1"
#854
0"
#855
b10011 !
b10011 $
1"
#856
0"
#857
b10100 !
b10100 $
1"
#858
0"
#859
b10101 !
b10101 $
1"
#860
0"
#861
b10110 !
b10110 $
1"
#862
0"
#863
b10111 !
b10111 $
1"
#864
0"
#865
b11000 !
b11000 $
1"
#866
0"
#867
b11001 !
b11001 $
1"
#868
0"
#869
b11010 !
b11010 $
1"
#870
0"
#871
b11011 !
b11011 $
1"
#872
0"
#873
b11100 !
b11100 $
1"
#874
0"
#875
b11101 !
b11101 $
1"
#876
0"
#877
b11110 !
b11110 $
1"
#878
0"
#879
b11111 !
b11111 $
1"
#880
0"
#881
b100000 !
b100000 $
1"
#882
0"
#883
b100001 !
b100001 $
1"
#884
0"
#885
b100010 !
b100010 $
1"
#886
0"
#887
b100011 !
b100011 $
1"
#888
0"
#889
b100100 !
b100100 $
1"
#890
0"
#891
b100101 !
b100101 $
1"
#892
0"
#893
b100110 !
b100110 $
1"
#894
0"
#895
b100111 !
b100111 $
1"
#896
0"
#897
b101000 !
b101000 $
1"
#898
0"
#899
b101001 !
b101001 $
1"
#900
0"
#901
b101010 !
b101010 $
1"
#902
0"
#903
b101011 !
b101011 $
1"
#904
0"
#905
b101100 !
b101100 $
1"
#906
0"
#907
b101101 !
b101101 $
1"
#908
0"
#909
b101110 !
b101110 $
1"
#910
0"
#911
b101111 !
b101111 $
1"
#912
0"
#913
b110000 !
b110000 $
1"
#914
0"
#915
b110001 !
b110001 $
1"
#916
0"
#917
b110010 !
b110010 $
1"
#918
0"
#919
b110011 !
b110011 $
1"
#920
0"
#921
b110100 !
b110100 $
1"
#922
0"
#923
b110101 !
b110101 $
1"
#924
0"
#925
b110110 !
b110110 $
1"
#926
0"
#927
b110111 !
b110111 $
1"
#928
0"
#929
b111000 !
b111000 $
1"
#930
0"
#931
b111001 !
b111001 $
1"
#932
0"
#933
b111010 !
b111010 $
1"
#934
0"
#935
b111011 !
b111011 $
1"
#936
0"
#937
b111100 !
b111100 $
1"
#938
0"
#939
b111101 !
b111101 $
1"
#940
0"
#941
b111110 !
b111110 $
1"
#942
0"
#943
b111111 !
b111111 $
1"
#944
0"
#945
b1000000 !
b1000000 $
1"
#946
0"
#947
b1000001 !
b1000001 $
1"
#948
0"
#949
b1000010 !
b1000010 $
1"
#950
0"
#951
b1000011 !
b1000011 $
1"
#952
0"
#953
b1000100 !
b1000100 $
1"
#954
0"
#955
b1000101 !
b1000101 $
1"
#956
0"
#957
b1000110 !
b1000110 $
1"
#958
0"
#959
b1000111 !
b1000111 $
1"
#960
0"
#961
b1001000 !
b1001000 $
1"
#962
0"
#963
b1001001 !
b1001001 $
1"
#964
0"
#965
b1001010 !
b1001010 $
1"
#966
0"
#967
b1001011 !
b1001011 $
1"
#968
0"
#969
b1001100 !
b1001100 $
1"
#970
0"
#971
b1001101 !
b1001101 $
1"
#972
0"
#973
b1001110 !
b1001110 $
1"
#974
0"
#975
b1001111 !
b1001111 $
1"
#976
0"
#977
b1010000 !
b1010000 $
1"
#978
0"
#979
b1010001 !
b1010001 $
1"
#980
0"
#981
b1010010 !
b1010010 $
1"
#982
0"
#983
b1010011 !
b1010011 $
1"
#984
0"
#985
b1010100 !
b1010100 $
1"
#986
0"
#987
b1010101 !
b1010101 $
1"
#988
0"
#989
b1010110 !
b1010110 $
1"
#990
0"
#991
b1010111 !
b1010111 $
1"
#992
0"
#993
b1011000 !
b1011000 $
1"
#994
0"
#995
b1011001 !
b1011001 $
1"
#996
0"
#997
b1011010 !
b1011010 $
1"
#998
0"
#999
b1011011 !
b1011011 $
1"
#1000
0"
#1001
b1011100 !
b1011100 $
1"
#1002
0"
#1003
b1011101 !
b1011101 $
1"
#1004
0"
#1005
b1011110 !
b1011110 $
1"
#1006
0"
#1007
b1011111 !
b1011111 $
1"
#1008
0"
#1009
b1100000 !
b1100000 $
1"
#1010
0"
#1011
b1100001 !
b1100001 $
1"
#1012
0"
#1013
b1100010 !
b1100010 $
1"
#1014
0"
#1015
b1100011 !
b1100011 $
1"
#1016
0"
#1017
b1100100 !
b1100100 $
1"
#1018
0"
#1019
b0 !
b0 $
1"
#1020
0"
#1021
b1 !
b1 $
1"
#1022
0"
#1023
b10 !
b10 $
1"
#1024
0"
#1025
b11 !
b11 $
1"
#1026
0"
#1027
b100 !
b100 $
1"
#1028
0"
#1029
b101 !
b101 $
1"
#1030
0"
#1031
b110 !
b110 $
1"
#1032
0"
#1033
b111 !
b111 $
1"
#1034
0"
#1035
b1000 !
b1000 $
1"
#1036
0"
#1037
b1001 !
b1001 $
1"
#1038
0"
#1039
b1010 !
b1010 $
1"
#1040
0"
#1041
b1011 !
b1011 $
1"
#1042
0"
#1043
b1100 !
b1100 $
1"
#1044
0"
#1045
b1101 !
b1101 $
1"
#1046
0"
#1047
b1110 !
b1110 $
1"
#1048
0"
#1049
b1111 !
b1111 $
1"
#1050
0"
#1051
b10000 !
b10000 $
1"
#1052
0"
#1053
b10001 !
b10001 $
1"
#1054
0"
#1055
b10010 !
b10010 $
1"
#1056
0"
#1057
b10011 !
b10011 $
1"
#1058
0"
#1059
b10100 !
b10100 $
1"
#1060
0"
#1061
b10101 !
b10101 $
1"
#1062
0"
#1063
b10110 !
b10110 $
1"
#1064
0"
#1065
b10111 !
b10111 $
1"
#1066
0"
#1067
b11000 !
b11000 $
1"
#1068
0"
#1069
b11001 !
b11001 $
1"
#1070
0"
#1071
b11010 !
b11010 $
1"
#1072
0"
#1073
b11011 !
b11011 $
1"
#1074
0"
#1075
b11100 !
b11100 $
1"
#1076
0"
#1077
b11101 !
b11101 $
1"
#1078
0"
#1079
b11110 !
b11110 $
1"
#1080
0"
#1081
b11111 !
b11111 $
1"
#1082
0"
#1083
b100000 !
b100000 $
1"
#1084
0"
#1085
b100001 !
b100001 $
1"
#1086
0"
#1087
b100010 !
b100010 $
1"
#1088
0"
#1089
b100011 !
b100011 $
1"
#1090
0"
#1091
b100100 !
b100100 $
1"
#1092
0"
#1093
b100101 !
b100101 $
1"
#1094
0"
#1095
b100110 !
b100110 $
1"
#1096
0"
#1097
b100111 !
b100111 $
1"
#1098
0"
#1099
b101000 !
b101000 $
1"
#1100
0"
#1101
b101001 !
b101001 $
1"
#1102
0"
#1103
b101010 !
b101010 $
1"
#1104
0"
#1105
b101011 !
b101011 $
1"
#1106
0"
#1107
b101100 !
b101100 $
1"
#1108
0"
#1109
b101101 !
b101101 $
1"
#1110
0"
#1111
b101110 !
b101110 $
1"
#1112
0"
#1113
b101111 !
b101111 $
1"
#1114
0"
#1115
b110000 !
b110000 $
1"
#1116
0"
#1117
b110001 !
b110001 $
1"
#1118
0"
#1119
b110010 !
b110010 $
1"
#1120
0"
#1121
b110011 !
b110011 $
1"
#1122
0"
#1123
b110100 !
b110100 $
1"
#1124
0"
#1125
b110101 !
b110101 $
1"
#1126
0"
#1127
b110110 !
b110110 $
1"
#1128
0"
#1129
b110111 !
b110111 $
1"
#1130
0"
#1131
b111000 !
b111000 $
1"
#1132
0"
#1133
b111001 !
b111001 $
1"
#1134
0"
#1135
b111010 !
b111010 $
1"
#1136
0"
#1137
b111011 !
b111011 $
1"
#1138
0"
#1139
b111100 !
b111100 $
1"
#1140
0"
#1141
b111101 !
b111101 $
1"
#1142
0"
#1143
b111110 !
b111110 $
1"
#1144
0"
#1145
b111111 !
b111111 $
1"
#1146
0"
#1147
b1000000 !
b1000000 $
1"
#1148
0"
#1149
b1000001 !
b1000001 $
1"
#1150
0"
#1151
b1000010 !
b1000010 $
1"
#1152
0"
#1153
b1000011 !
b1000011 $
1"
#1154
0"
#1155
b1000100 !
b1000100 $
1"
#1156
0"
#1157
b1000101 !
b1000101 $
1"
#1158
0"
#1159
b1000110 !
b1000110 $
1"
#1160
0"
#1161
b1000111 !
b1000111 $
1"
#1162
0"
#1163
b1001000 !
b1001000 $
1"
#1164
0"
#1165
b1001001 !
b1001001 $
1"
#1166
0"
